dumb_maybe/__init__.py
dumb_maybe-0.0.4.dist-info/METADATA
dumb_maybe-0.0.4.dist-info/WHEEL
dumb_maybe-0.0.4.dist-info/licenses/LICENSE.txt
dumb_maybe-0.0.4.dist-info/RECORD
