Metadata-Version: 2.4
Name: dumb-maybe
Version: 0.0.4
Summary: A Very Dumb Maybe Type
Project-URL: Homepage, https://github.com/TheMadman/dumb-maybe
Author-email: Marcus Harrison <marcus@harrisonland.co.uk>
License-File: LICENSE.txt
Classifier: Operating System :: OS Independent
Classifier: Programming Language :: Python :: 3
Requires-Python: >=3.8
